{
  "disableSources": false,
  "entryPoints": ["src/index.ts", "./package.json"],
  "excludeExternals": false,
  "excludePrivate": true,
  "excludeProtected": true,
  "includeVersion": true,
  "out": "api-docs",
  "theme": "pages-plugin",
  "media": "media",
  "gaID": "G-LTZL26963K",
    "pages": {
      "groups": [
        {
          "title": "Getting Started",
          "pages": [
            {
              "title": "Installation",
              "source": "./docs/getting-started/installation.md"
            },
            {
              "title": "Administration",
              "source": "./docs/getting-started/admin.md"
            }
          ]
        }
      ]
    }
}
